CHANGES.rst
COPYING
COPYING.LESSER
MANIFEST.in
README.rst
bootstrap-buildout.py
buildout.cfg
ez_setup.py
setup.cfg
setup.py
tox.ini
./mete0r/__init__.py
./mete0r/recipe/__init__.py
./mete0r/recipe/localconfig/__init__.py
./mete0r/recipe/localconfig/recipe.py
./mete0r/recipe/localconfig/tests/__init__.py
./mete0r/recipe/localconfig/tests/test_recipe.py
mete0r/__init__.py
mete0r.recipe.localconfig.egg-info/PKG-INFO
mete0r.recipe.localconfig.egg-info/SOURCES.txt
mete0r.recipe.localconfig.egg-info/dependency_links.txt
mete0r.recipe.localconfig.egg-info/entry_points.txt
mete0r.recipe.localconfig.egg-info/namespace_packages.txt
mete0r.recipe.localconfig.egg-info/requires.txt
mete0r.recipe.localconfig.egg-info/top_level.txt
mete0r.recipe.localconfig.egg-info/zip-safe
mete0r/recipe/__init__.py
mete0r/recipe/localconfig/__init__.py
mete0r/recipe/localconfig/recipe.py
mete0r/recipe/localconfig/tests/__init__.py
mete0r/recipe/localconfig/tests/test_recipe.py